mono2repo/__init__.py
mono2repo/mono2repo.py
mono2repo-0.1.2.dist-info/METADATA
mono2repo-0.1.2.dist-info/WHEEL
mono2repo-0.1.2.dist-info/entry_points.txt
mono2repo-0.1.2.dist-info/top_level.txt
mono2repo-0.1.2.dist-info/RECORD
