Metadata-Version: 2.1
Name: mono2repo
Version: 0.1.2
Summary: create a standalone repo from a monorepo subdir.
Author-email: Antonio Cavallo <a.cavallo@cavallinux.eu>
License: MIT
Project-URL: Source, https://github.com/cav71/mono2repo
Project-URL: Issues, https://github.com/cav71/mono2repo/issues
Project-URL: Documentation, https://github.com/cav71/mono2repo
Classifier: Development Status :: 4 - Beta
Classifier: Programming Language :: Python
Classifier: Programming Language :: Python :: 3.9
Classifier: Programming Language :: Python :: 3.10
Classifier: Programming Language :: Python :: 3.11
Classifier: Programming Language :: Python :: 3.12
Classifier: Programming Language :: Python :: 3.13
Requires-Python: >=3.9
